fpinpy/__init__.py
fpinpy/collections/__init__.py
fpinpy/collections/map.py
fpinpy/collections/singly_linked_list.py
fpinpy/meta/__init__.py
fpinpy/meta/decorators.py
fpinpy/meta/singleton.py
fpinpy/meta/type_info.py
fpinpy/readers/__init__.py
fpinpy/readers/by_line.py
fpinpy/readers/iniconfig.py
fpinpy/result/__init__.py
fpinpy/result/result_using_bool_distinguisher.py
fpinpy/result/result_using_subclass_distinguisher.py
fpinpy-1.2.2.dist-info/METADATA
fpinpy-1.2.2.dist-info/WHEEL
fpinpy-1.2.2.dist-info/top_level.txt
fpinpy-1.2.2.dist-info/RECORD
