Metadata-Version: 2.1
Name: fpinpy
Version: 1.2.2
Summary: A functional library for Python.
Home-page: https://github.com/metzenseifner/py_fpinpy
Author: Jonathan L. Komar
Author-email: jonathan.komar@uibk.ac.at
License: MIT
Classifier: License :: OSI Approved :: MIT License
Classifier: Programming Language :: Python :: 3
Classifier: Topic :: Utilities
Classifier: Topic :: Software Development :: Libraries
